[
  {
    "hash": "a0fdd1c7a9226099391b5b0af4496ee0",
    "title": "Your 2024 Spirit of KUAC Award Winner is Marie Olesen!",
    "summary": "2024\u2019s Spirit of KUAC volunteer award goes to Marie Olesen! Marie has given generously of her time as on-air talent, phone bank supervisor, and d-anything volunteer. Marie brings her infectious joy and passion for KUAC to everything she does, and truly embodies the spirit of KUAC. Thank you Marie!",
    "source": "KUAC Fairbanks",
    "sourceUrl": "KUAC Fairbanks",
    "articleUrl": "https://kuac.org/your-2024-spirit-of-kuac-award-winner-is-marie-olesen/",
    "url": "https://kuac.org/your-2024-spirit-of-kuac-award-winner-is-marie-olesen/",
    "timestamp": "2024-09-02T03:53:00+00:00",
    "topic": "Radio",
    "section": "Radio"
  }
]