[
  {
    "hash": "ef6c40e37486f494b0af59216f2fd026",
    "title": "Funding for Native Americans Down 30%",
    "summary": "U.S. foundation support benefiting Native Americans declined from 0.5 percent to 0.3 percent of total foundation giving. According to Foundation Funding for Native American Issues and Peoples , released by Native Americans in Philanthropy (NAP) and the Foundation Center, total grant dollars targetin...",
    "source": "Alaska Conservation Foundation",
    "sourceUrl": "Alaska Conservation Foundation",
    "articleUrl": "https://alaskaconservation.org/2011/06/funding-native-americans-30/",
    "url": "https://alaskaconservation.org/2011/06/funding-native-americans-30/",
    "timestamp": "2011-06-14T19:29:00+00:00",
    "topic": "Environment",
    "section": "Environment"
  }
]