[
  {
    "hash": "a1c4eadd1418c92f51c26aba7b69f48d",
    "title": "Join Us! Finance & Operations Specialist Position Open",
    "summary": "ACF has an exciting job opportunity available immediately! We are looking for a part-time Finance and Operations Specialist. This position supports the Director of Finance and Operations with accounting, human resources, facilities and IT responsibilities. Finance duties include budgeting, financial...",
    "source": "Alaska Conservation Foundation",
    "sourceUrl": "Alaska Conservation Foundation",
    "articleUrl": "https://alaskaconservation.org/2011/01/join-finance-operations-specialist-position-open/",
    "url": "https://alaskaconservation.org/2011/01/join-finance-operations-specialist-position-open/",
    "timestamp": "2011-01-12T03:05:07+00:00",
    "topic": "Environment",
    "section": "Environment"
  }
]