[
  {
    "hash": "3715d17acd49235c41ea4bf91f7805cb",
    "source": "Sealaska Corporation",
    "category": "Native",
    "title": "Sealaska Makes First Major Investment since New Strategic Plan in 2012",
    "link": "https://www.sealaska.com/stories/sealaska-makes-first-major-investment-since-new-strategic-plan-2012/",
    "published": "Tue, 10 May 2016 18:32:02 +0000",
    "summary": "Sealaska has purchased a minority interest in Independent Packers Corporation (IPC), a custom seafood processor located in Seattle, Washington. Sealaska embarked on a strategic plan in late 2012 to restructure operations and improve profitability. The plan focused on re-engineering its businesses to...",
    "dataTag": "[Region: Statewide] [Category: Native]",
    "sourceAttribution": "Source: Sealaska Corporation",
    "imageUrl": null,
    "timestamp": "2016-05-10T18:32:02+00:00",
    "impactScore": 38,
    "region": "Southeast",
    "sector": "native-affairs",
    "urgency": "background",
    "entitySlugs": [
      "sealaska"
    ],
    "relatedSignalIds": [
      "d1d65670d2880a6ec2f76551e1aa62fd",
      "f53b67edbc8d0466a84d8d25f06c7e0a",
      "6470b9ad0cb4a4370beb81a0e6af7dc8",
      "9c51c80b62437d3136df36a26884322a",
      "74ae0333e2c1af267362b8b38f04eee7"
    ]
  }
]