[
  {
    "hash": "3f4d95fa99be34ef22c5cd1461dc16b8",
    "title": "Chugach educates Harvard",
    "summary": "Eleven years ago, Harvard University set a goal to reduce their greenhouse emissions by 30 percent. Through an aggressive and ambitious 10-year program, Harvard did it. In fact, in some areas Harvard exceeded their goal and attained a 40 percent reduction. Now, Harvard is reaching beyond the boundaries of its campus and seeking ways to further reduce their carbon footprint. To this end, Harvard students Michael Maruca and Vi...",
    "source": "Chugach Alaska Corp",
    "sourceUrl": "Chugach Alaska Corp",
    "articleUrl": "https://www.chugach.com/news-story/innovations-3",
    "url": "https://www.chugach.com/news-story/innovations-3",
    "timestamp": "2017-03-19T05:00:00+00:00",
    "topic": "Native",
    "section": "Native"
  }
]