[
  {
    "hash": "15f169fa999222443318a05cbc7f1f2b",
    "id": "AK25052058",
    "source": "Alaska State Troopers",
    "category": "Safety",
    "title": "AST Trespassing/VCOR: Tok [AK25052058]",
    "link": "https://dailydispatch.dps.alaska.gov/Home/DisplayIncident?incidentNumber=AK25052058",
    "sourceUrl": "https://dailydispatch.dps.alaska.gov",
    "articleUrl": "https://dailydispatch.dps.alaska.gov/Home/DisplayIncident?incidentNumber=AK25052058",
    "favicon": "https://www.dps.alaska.gov/favicon.ico",
    "location": "Tok",
    "incident_type": "Trespassing/VCOR",
    "summary": "On May 30th, 2025, at approximately 1755 hours Tok AST received a report of a trespassing. Investigation found Roylon Mark, age 39 of Tetlin, had committed the crimes of Trespassing II and VCOR x8. He was arrested and remanded to FCC.",
    "dataTag": "[Region: Interior] [Category: Law Enforcement]",
    "sourceAttribution": "Multiple Sources (2 reports)",
    "section": "Safety",
    "sourceLean": "neutral",
    "topic": "Trespassing/VCOR",
    "timestamp": "2025-05-30T23:40:09+00:00",
    "scraped_at": "2026-03-24T00:08:13.967287+00:00",
    "posted": "5/30/2025 11:40:09 PM by DPS\\bbschwarz",
    "entities": {
      "suspects": [],
      "charges": [],
      "bac": null,
      "facility": {
        "code": "FCC",
        "name": "Fairbanks Correctional Center"
      },
      "bail": {
        "status": "unknown",
        "amount": null
      },
      "outcome": "arrested",
      "incident_datetime": null,
      "co_agencies": [],
      "address_detail": "approximately 1755 hours Tok AST received a report of a trespassing",
      "detachment": "D Detachment",
      "officer_id": "bbschwarz"
    },
    "lat": 63.3367,
    "lng": -142.9856,
    "relatedSignalIds": [
      "80bf6c54ac89d4979c8e43cb665390e8",
      "2fe4a75ac8fe2054f7e8bd3ec5f5ceb4",
      "21005a1aec05868317f6315e030a70df",
      "37db83d95532bb01ab952ddd98f1c990",
      "a9eb1326443207df38d1ebcd214452bb"
    ],
    "isGrouped": true,
    "subSources": [
      {
        "hash": "15f169fa999222443318a05cbc7f1f2b",
        "id": "AK25052058",
        "source": "Alaska State Troopers",
        "category": "Safety",
        "title": "AST Trespassing/VCOR: Tok [AK25052058]",
        "link": "https://dailydispatch.dps.alaska.gov/Home/DisplayIncident?incidentNumber=AK25052058",
        "sourceUrl": "https://dailydispatch.dps.alaska.gov",
        "articleUrl": "https://dailydispatch.dps.alaska.gov/Home/DisplayIncident?incidentNumber=AK25052058",
        "favicon": "https://www.dps.alaska.gov/favicon.ico",
        "location": "Tok",
        "incident_type": "Trespassing/VCOR",
        "summary": "On May 30th, 2025, at approximately 1755 hours Tok AST received a report of a trespassing. Investigation found Roylon Mark, age 39 of Tetlin, had committed the crimes of Trespassing II and VCOR x8. He was arrested and remanded to FCC.",
        "dataTag": "[Region: Interior] [Category: Law Enforcement]",
        "sourceAttribution": "Source: Alaska State Troopers Daily Dispatch",
        "section": "Safety",
        "sourceLean": "neutral",
        "topic": "Trespassing/VCOR",
        "timestamp": "2025-05-30T23:40:09+00:00",
        "scraped_at": "2026-03-24T00:08:13.967287+00:00",
        "posted": "5/30/2025 11:40:09 PM by DPS\\bbschwarz",
        "entities": {
          "suspects": [],
          "charges": [],
          "bac": null,
          "facility": {
            "code": "FCC",
            "name": "Fairbanks Correctional Center"
          },
          "bail": {
            "status": "unknown",
            "amount": null
          },
          "outcome": "arrested",
          "incident_datetime": null,
          "co_agencies": [],
          "address_detail": "approximately 1755 hours Tok AST received a report of a trespassing",
          "detachment": "D Detachment",
          "officer_id": "bbschwarz"
        },
        "lat": 63.3367,
        "lng": -142.9856,
        "relatedSignalIds": []
      },
      {
        "hash": "188cb0f874eb7892d66961f02cb5e534",
        "id": "AK25052087",
        "source": "Alaska State Troopers",
        "category": "Safety",
        "title": "AST Assault DV: Tok [AK25052087]",
        "link": "https://dailydispatch.dps.alaska.gov/Home/DisplayIncident?incidentNumber=AK25052087",
        "sourceUrl": "https://dailydispatch.dps.alaska.gov",
        "articleUrl": "https://dailydispatch.dps.alaska.gov/Home/DisplayIncident?incidentNumber=AK25052087",
        "favicon": "https://www.dps.alaska.gov/favicon.ico",
        "location": "Tok",
        "incident_type": "Assault DV",
        "summary": "On 5/30/2025, Alaska State Troopers in Tok responded to an Assault DV. Investigation revealed Wilbur Karmun to have committed Assault in the Fourth Degree and Assault in the Presence of a Child. Wilbur was arrested and charged.",
        "dataTag": "[Region: Interior] [Category: Law Enforcement]",
        "sourceAttribution": "Source: Alaska State Troopers Daily Dispatch",
        "section": "Safety",
        "sourceLean": "neutral",
        "topic": "Assault DV",
        "timestamp": "2025-05-30T23:38:20+00:00",
        "scraped_at": "2026-03-24T00:08:13.967017+00:00",
        "posted": "5/30/2025 11:38:20 PM by DPS\\cdbuie",
        "entities": {
          "suspects": [],
          "charges": [],
          "bac": null,
          "facility": null,
          "bail": {
            "status": "unknown",
            "amount": null
          },
          "outcome": "arrested",
          "incident_datetime": null,
          "co_agencies": [],
          "address_detail": "revealed Wilbur Karmun to have committed Assault in the Fourth Degree",
          "detachment": "D Detachment",
          "officer_id": "cdbuie"
        },
        "lat": 63.3367,
        "lng": -142.9856,
        "relatedSignalIds": []
      },
      {
        "hash": "15f169fa999222443318a05cbc7f1f2b",
        "id": "AK25052058",
        "source": "Alaska State Troopers",
        "category": "Safety",
        "title": "AST Trespassing/VCOR: Tok [AK25052058]",
        "link": "https://dailydispatch.dps.alaska.gov/Home/DisplayIncident?incidentNumber=AK25052058",
        "sourceUrl": "https://dailydispatch.dps.alaska.gov",
        "articleUrl": "https://dailydispatch.dps.alaska.gov/Home/DisplayIncident?incidentNumber=AK25052058",
        "favicon": "https://www.dps.alaska.gov/favicon.ico",
        "location": "Tok",
        "incident_type": "Trespassing/VCOR",
        "summary": "On May 30th, 2025, at approximately 1755 hours Tok AST received a report of a trespassing. Investigation found Roylon Mark, age 39 of Tetlin, had committed the crimes of Trespassing II and VCOR x8. He was arrested and remanded to FCC.",
        "dataTag": "[Region: Interior] [Category: Law Enforcement]",
        "sourceAttribution": "Multiple Sources (2 reports)",
        "section": "Safety",
        "sourceLean": "neutral",
        "topic": "Trespassing/VCOR",
        "timestamp": "2025-05-30T23:40:09+00:00",
        "scraped_at": "2026-03-24T00:08:13.967287+00:00",
        "posted": "5/30/2025 11:40:09 PM by DPS\\bbschwarz",
        "entities": {
          "suspects": [],
          "charges": [],
          "bac": null,
          "facility": {
            "code": "FCC",
            "name": "Fairbanks Correctional Center"
          },
          "bail": {
            "status": "unknown",
            "amount": null
          },
          "outcome": "arrested",
          "incident_datetime": null,
          "co_agencies": [],
          "address_detail": "approximately 1755 hours Tok AST received a report of a trespassing",
          "detachment": "D Detachment",
          "officer_id": "bbschwarz"
        },
        "lat": 63.3367,
        "lng": -142.9856,
        "relatedSignalIds": [],
        "impactScore": 45
      },
      {
        "hash": "188cb0f874eb7892d66961f02cb5e534",
        "id": "AK25052087",
        "source": "Alaska State Troopers",
        "category": "Safety",
        "title": "AST Assault DV: Tok [AK25052087]",
        "link": "https://dailydispatch.dps.alaska.gov/Home/DisplayIncident?incidentNumber=AK25052087",
        "sourceUrl": "https://dailydispatch.dps.alaska.gov",
        "articleUrl": "https://dailydispatch.dps.alaska.gov/Home/DisplayIncident?incidentNumber=AK25052087",
        "favicon": "https://www.dps.alaska.gov/favicon.ico",
        "location": "Tok",
        "incident_type": "Assault DV",
        "summary": "On 5/30/2025, Alaska State Troopers in Tok responded to an Assault DV. Investigation revealed Wilbur Karmun to have committed Assault in the Fourth Degree and Assault in the Presence of a Child. Wilbur was arrested and charged.",
        "dataTag": "[Region: Interior] [Category: Law Enforcement]",
        "sourceAttribution": "Source: Alaska State Troopers Daily Dispatch",
        "section": "Safety",
        "sourceLean": "neutral",
        "topic": "Assault DV",
        "timestamp": "2025-05-30T23:38:20+00:00",
        "scraped_at": "2026-03-24T00:08:13.967017+00:00",
        "posted": "5/30/2025 11:38:20 PM by DPS\\cdbuie",
        "entities": {
          "suspects": [],
          "charges": [],
          "bac": null,
          "facility": null,
          "bail": {
            "status": "unknown",
            "amount": null
          },
          "outcome": "arrested",
          "incident_datetime": null,
          "co_agencies": [],
          "address_detail": "revealed Wilbur Karmun to have committed Assault in the Fourth Degree",
          "detachment": "D Detachment",
          "officer_id": "cdbuie"
        },
        "lat": 63.3367,
        "lng": -142.9856,
        "relatedSignalIds": []
      },
      {
        "hash": "15f169fa999222443318a05cbc7f1f2b",
        "id": "AK25052058",
        "source": "Alaska State Troopers",
        "category": "Safety",
        "title": "AST Trespassing/VCOR: Tok [AK25052058]",
        "link": "https://dailydispatch.dps.alaska.gov/Home/DisplayIncident?incidentNumber=AK25052058",
        "sourceUrl": "https://dailydispatch.dps.alaska.gov",
        "articleUrl": "https://dailydispatch.dps.alaska.gov/Home/DisplayIncident?incidentNumber=AK25052058",
        "favicon": "https://www.dps.alaska.gov/favicon.ico",
        "location": "Tok",
        "incident_type": "Trespassing/VCOR",
        "summary": "On May 30th, 2025, at approximately 1755 hours Tok AST received a report of a trespassing. Investigation found Roylon Mark, age 39 of Tetlin, had committed the crimes of Trespassing II and VCOR x8. He was arrested and remanded to FCC.",
        "dataTag": "[Region: Interior] [Category: Law Enforcement]",
        "sourceAttribution": "Multiple Sources (2 reports)",
        "section": "Safety",
        "sourceLean": "neutral",
        "topic": "Trespassing/VCOR",
        "timestamp": "2025-05-30T23:40:09+00:00",
        "scraped_at": "2026-03-24T00:08:13.967287+00:00",
        "posted": "5/30/2025 11:40:09 PM by DPS\\bbschwarz",
        "entities": {
          "suspects": [],
          "charges": [],
          "bac": null,
          "facility": {
            "code": "FCC",
            "name": "Fairbanks Correctional Center"
          },
          "bail": {
            "status": "unknown",
            "amount": null
          },
          "outcome": "arrested",
          "incident_datetime": null,
          "co_agencies": [],
          "address_detail": "approximately 1755 hours Tok AST received a report of a trespassing",
          "detachment": "D Detachment",
          "officer_id": "bbschwarz"
        },
        "lat": 63.3367,
        "lng": -142.9856,
        "relatedSignalIds": [],
        "impactScore": 50
      },
      {
        "hash": "188cb0f874eb7892d66961f02cb5e534",
        "id": "AK25052087",
        "source": "Alaska State Troopers",
        "category": "Safety",
        "title": "AST Assault DV: Tok [AK25052087]",
        "link": "https://dailydispatch.dps.alaska.gov/Home/DisplayIncident?incidentNumber=AK25052087",
        "sourceUrl": "https://dailydispatch.dps.alaska.gov",
        "articleUrl": "https://dailydispatch.dps.alaska.gov/Home/DisplayIncident?incidentNumber=AK25052087",
        "favicon": "https://www.dps.alaska.gov/favicon.ico",
        "location": "Tok",
        "incident_type": "Assault DV",
        "summary": "On 5/30/2025, Alaska State Troopers in Tok responded to an Assault DV. Investigation revealed Wilbur Karmun to have committed Assault in the Fourth Degree and Assault in the Presence of a Child. Wilbur was arrested and charged.",
        "dataTag": "[Region: Interior] [Category: Law Enforcement]",
        "sourceAttribution": "Source: Alaska State Troopers Daily Dispatch",
        "section": "Safety",
        "sourceLean": "neutral",
        "topic": "Assault DV",
        "timestamp": "2025-05-30T23:38:20+00:00",
        "scraped_at": "2026-03-24T00:08:13.967017+00:00",
        "posted": "5/30/2025 11:38:20 PM by DPS\\cdbuie",
        "entities": {
          "suspects": [],
          "charges": [],
          "bac": null,
          "facility": null,
          "bail": {
            "status": "unknown",
            "amount": null
          },
          "outcome": "arrested",
          "incident_datetime": null,
          "co_agencies": [],
          "address_detail": "revealed Wilbur Karmun to have committed Assault in the Fourth Degree",
          "detachment": "D Detachment",
          "officer_id": "cdbuie"
        },
        "lat": 63.3367,
        "lng": -142.9856,
        "relatedSignalIds": []
      },
      {
        "hash": "15f169fa999222443318a05cbc7f1f2b",
        "id": "AK25052058",
        "source": "Alaska State Troopers",
        "category": "Safety",
        "title": "AST Trespassing/VCOR: Tok [AK25052058]",
        "link": "https://dailydispatch.dps.alaska.gov/Home/DisplayIncident?incidentNumber=AK25052058",
        "sourceUrl": "https://dailydispatch.dps.alaska.gov",
        "articleUrl": "https://dailydispatch.dps.alaska.gov/Home/DisplayIncident?incidentNumber=AK25052058",
        "favicon": "https://www.dps.alaska.gov/favicon.ico",
        "location": "Tok",
        "incident_type": "Trespassing/VCOR",
        "summary": "On May 30th, 2025, at approximately 1755 hours Tok AST received a report of a trespassing. Investigation found Roylon Mark, age 39 of Tetlin, had committed the crimes of Trespassing II and VCOR x8. He was arrested and remanded to FCC.",
        "dataTag": "[Region: Interior] [Category: Law Enforcement]",
        "sourceAttribution": "Multiple Sources (2 reports)",
        "section": "Safety",
        "sourceLean": "neutral",
        "topic": "Trespassing/VCOR",
        "timestamp": "2025-05-30T23:40:09+00:00",
        "scraped_at": "2026-03-24T00:08:13.967287+00:00",
        "posted": "5/30/2025 11:40:09 PM by DPS\\bbschwarz",
        "entities": {
          "suspects": [],
          "charges": [],
          "bac": null,
          "facility": {
            "code": "FCC",
            "name": "Fairbanks Correctional Center"
          },
          "bail": {
            "status": "unknown",
            "amount": null
          },
          "outcome": "arrested",
          "incident_datetime": null,
          "co_agencies": [],
          "address_detail": "approximately 1755 hours Tok AST received a report of a trespassing",
          "detachment": "D Detachment",
          "officer_id": "bbschwarz"
        },
        "lat": 63.3367,
        "lng": -142.9856,
        "relatedSignalIds": [],
        "impactScore": 55
      },
      {
        "hash": "188cb0f874eb7892d66961f02cb5e534",
        "id": "AK25052087",
        "source": "Alaska State Troopers",
        "category": "Safety",
        "title": "AST Assault DV: Tok [AK25052087]",
        "link": "https://dailydispatch.dps.alaska.gov/Home/DisplayIncident?incidentNumber=AK25052087",
        "sourceUrl": "https://dailydispatch.dps.alaska.gov",
        "articleUrl": "https://dailydispatch.dps.alaska.gov/Home/DisplayIncident?incidentNumber=AK25052087",
        "favicon": "https://www.dps.alaska.gov/favicon.ico",
        "location": "Tok",
        "incident_type": "Assault DV",
        "summary": "On 5/30/2025, Alaska State Troopers in Tok responded to an Assault DV. Investigation revealed Wilbur Karmun to have committed Assault in the Fourth Degree and Assault in the Presence of a Child. Wilbur was arrested and charged.",
        "dataTag": "[Region: Interior] [Category: Law Enforcement]",
        "sourceAttribution": "Source: Alaska State Troopers Daily Dispatch",
        "section": "Safety",
        "sourceLean": "neutral",
        "topic": "Assault DV",
        "timestamp": "2025-05-30T23:38:20+00:00",
        "scraped_at": "2026-03-24T00:08:13.967017+00:00",
        "posted": "5/30/2025 11:38:20 PM by DPS\\cdbuie",
        "entities": {
          "suspects": [],
          "charges": [],
          "bac": null,
          "facility": null,
          "bail": {
            "status": "unknown",
            "amount": null
          },
          "outcome": "arrested",
          "incident_datetime": null,
          "co_agencies": [],
          "address_detail": "revealed Wilbur Karmun to have committed Assault in the Fourth Degree",
          "detachment": "D Detachment",
          "officer_id": "cdbuie"
        },
        "lat": 63.3367,
        "lng": -142.9856,
        "relatedSignalIds": []
      },
      {
        "hash": "15f169fa999222443318a05cbc7f1f2b",
        "id": "AK25052058",
        "source": "Alaska State Troopers",
        "category": "Safety",
        "title": "AST Trespassing/VCOR: Tok [AK25052058]",
        "link": "https://dailydispatch.dps.alaska.gov/Home/DisplayIncident?incidentNumber=AK25052058",
        "sourceUrl": "https://dailydispatch.dps.alaska.gov",
        "articleUrl": "https://dailydispatch.dps.alaska.gov/Home/DisplayIncident?incidentNumber=AK25052058",
        "favicon": "https://www.dps.alaska.gov/favicon.ico",
        "location": "Tok",
        "incident_type": "Trespassing/VCOR",
        "summary": "On May 30th, 2025, at approximately 1755 hours Tok AST received a report of a trespassing. Investigation found Roylon Mark, age 39 of Tetlin, had committed the crimes of Trespassing II and VCOR x8. He was arrested and remanded to FCC.",
        "dataTag": "[Region: Interior] [Category: Law Enforcement]",
        "sourceAttribution": "Multiple Sources (2 reports)",
        "section": "Safety",
        "sourceLean": "neutral",
        "topic": "Trespassing/VCOR",
        "timestamp": "2025-05-30T23:40:09+00:00",
        "scraped_at": "2026-03-24T00:08:13.967287+00:00",
        "posted": "5/30/2025 11:40:09 PM by DPS\\bbschwarz",
        "entities": {
          "suspects": [],
          "charges": [],
          "bac": null,
          "facility": {
            "code": "FCC",
            "name": "Fairbanks Correctional Center"
          },
          "bail": {
            "status": "unknown",
            "amount": null
          },
          "outcome": "arrested",
          "incident_datetime": null,
          "co_agencies": [],
          "address_detail": "approximately 1755 hours Tok AST received a report of a trespassing",
          "detachment": "D Detachment",
          "officer_id": "bbschwarz"
        },
        "lat": 63.3367,
        "lng": -142.9856,
        "relatedSignalIds": [],
        "impactScore": 60
      },
      {
        "hash": "188cb0f874eb7892d66961f02cb5e534",
        "id": "AK25052087",
        "source": "Alaska State Troopers",
        "category": "Safety",
        "title": "AST Assault DV: Tok [AK25052087]",
        "link": "https://dailydispatch.dps.alaska.gov/Home/DisplayIncident?incidentNumber=AK25052087",
        "sourceUrl": "https://dailydispatch.dps.alaska.gov",
        "articleUrl": "https://dailydispatch.dps.alaska.gov/Home/DisplayIncident?incidentNumber=AK25052087",
        "favicon": "https://www.dps.alaska.gov/favicon.ico",
        "location": "Tok",
        "incident_type": "Assault DV",
        "summary": "On 5/30/2025, Alaska State Troopers in Tok responded to an Assault DV. Investigation revealed Wilbur Karmun to have committed Assault in the Fourth Degree and Assault in the Presence of a Child. Wilbur was arrested and charged.",
        "dataTag": "[Region: Interior] [Category: Law Enforcement]",
        "sourceAttribution": "Source: Alaska State Troopers Daily Dispatch",
        "section": "Safety",
        "sourceLean": "neutral",
        "topic": "Assault DV",
        "timestamp": "2025-05-30T23:38:20+00:00",
        "scraped_at": "2026-03-24T00:08:13.967017+00:00",
        "posted": "5/30/2025 11:38:20 PM by DPS\\cdbuie",
        "entities": {
          "suspects": [],
          "charges": [],
          "bac": null,
          "facility": null,
          "bail": {
            "status": "unknown",
            "amount": null
          },
          "outcome": "arrested",
          "incident_datetime": null,
          "co_agencies": [],
          "address_detail": "revealed Wilbur Karmun to have committed Assault in the Fourth Degree",
          "detachment": "D Detachment",
          "officer_id": "cdbuie"
        },
        "lat": 63.3367,
        "lng": -142.9856,
        "relatedSignalIds": []
      },
      {
        "hash": "15f169fa999222443318a05cbc7f1f2b",
        "id": "AK25052058",
        "source": "Alaska State Troopers",
        "category": "Safety",
        "title": "AST Trespassing/VCOR: Tok [AK25052058]",
        "link": "https://dailydispatch.dps.alaska.gov/Home/DisplayIncident?incidentNumber=AK25052058",
        "sourceUrl": "https://dailydispatch.dps.alaska.gov",
        "articleUrl": "https://dailydispatch.dps.alaska.gov/Home/DisplayIncident?incidentNumber=AK25052058",
        "favicon": "https://www.dps.alaska.gov/favicon.ico",
        "location": "Tok",
        "incident_type": "Trespassing/VCOR",
        "summary": "On May 30th, 2025, at approximately 1755 hours Tok AST received a report of a trespassing. Investigation found Roylon Mark, age 39 of Tetlin, had committed the crimes of Trespassing II and VCOR x8. He was arrested and remanded to FCC.",
        "dataTag": "[Region: Interior] [Category: Law Enforcement]",
        "sourceAttribution": "Multiple Sources (2 reports)",
        "section": "Safety",
        "sourceLean": "neutral",
        "topic": "Trespassing/VCOR",
        "timestamp": "2025-05-30T23:40:09+00:00",
        "scraped_at": "2026-03-24T00:08:13.967287+00:00",
        "posted": "5/30/2025 11:40:09 PM by DPS\\bbschwarz",
        "entities": {
          "suspects": [],
          "charges": [],
          "bac": null,
          "facility": {
            "code": "FCC",
            "name": "Fairbanks Correctional Center"
          },
          "bail": {
            "status": "unknown",
            "amount": null
          },
          "outcome": "arrested",
          "incident_datetime": null,
          "co_agencies": [],
          "address_detail": "approximately 1755 hours Tok AST received a report of a trespassing",
          "detachment": "D Detachment",
          "officer_id": "bbschwarz"
        },
        "lat": 63.3367,
        "lng": -142.9856,
        "relatedSignalIds": [],
        "impactScore": 65
      },
      {
        "hash": "188cb0f874eb7892d66961f02cb5e534",
        "id": "AK25052087",
        "source": "Alaska State Troopers",
        "category": "Safety",
        "title": "AST Assault DV: Tok [AK25052087]",
        "link": "https://dailydispatch.dps.alaska.gov/Home/DisplayIncident?incidentNumber=AK25052087",
        "sourceUrl": "https://dailydispatch.dps.alaska.gov",
        "articleUrl": "https://dailydispatch.dps.alaska.gov/Home/DisplayIncident?incidentNumber=AK25052087",
        "favicon": "https://www.dps.alaska.gov/favicon.ico",
        "location": "Tok",
        "incident_type": "Assault DV",
        "summary": "On 5/30/2025, Alaska State Troopers in Tok responded to an Assault DV. Investigation revealed Wilbur Karmun to have committed Assault in the Fourth Degree and Assault in the Presence of a Child. Wilbur was arrested and charged.",
        "dataTag": "[Region: Interior] [Category: Law Enforcement]",
        "sourceAttribution": "Source: Alaska State Troopers Daily Dispatch",
        "section": "Safety",
        "sourceLean": "neutral",
        "topic": "Assault DV",
        "timestamp": "2025-05-30T23:38:20+00:00",
        "scraped_at": "2026-03-24T00:08:13.967017+00:00",
        "posted": "5/30/2025 11:38:20 PM by DPS\\cdbuie",
        "entities": {
          "suspects": [],
          "charges": [],
          "bac": null,
          "facility": null,
          "bail": {
            "status": "unknown",
            "amount": null
          },
          "outcome": "arrested",
          "incident_datetime": null,
          "co_agencies": [],
          "address_detail": "revealed Wilbur Karmun to have committed Assault in the Fourth Degree",
          "detachment": "D Detachment",
          "officer_id": "cdbuie"
        },
        "lat": 63.3367,
        "lng": -142.9856,
        "relatedSignalIds": []
      },
      {
        "hash": "15f169fa999222443318a05cbc7f1f2b",
        "id": "AK25052058",
        "source": "Alaska State Troopers",
        "category": "Safety",
        "title": "AST Trespassing/VCOR: Tok [AK25052058]",
        "link": "https://dailydispatch.dps.alaska.gov/Home/DisplayIncident?incidentNumber=AK25052058",
        "sourceUrl": "https://dailydispatch.dps.alaska.gov",
        "articleUrl": "https://dailydispatch.dps.alaska.gov/Home/DisplayIncident?incidentNumber=AK25052058",
        "favicon": "https://www.dps.alaska.gov/favicon.ico",
        "location": "Tok",
        "incident_type": "Trespassing/VCOR",
        "summary": "On May 30th, 2025, at approximately 1755 hours Tok AST received a report of a trespassing. Investigation found Roylon Mark, age 39 of Tetlin, had committed the crimes of Trespassing II and VCOR x8. He was arrested and remanded to FCC.",
        "dataTag": "[Region: Interior] [Category: Law Enforcement]",
        "sourceAttribution": "Multiple Sources (2 reports)",
        "section": "Safety",
        "sourceLean": "neutral",
        "topic": "Trespassing/VCOR",
        "timestamp": "2025-05-30T23:40:09+00:00",
        "scraped_at": "2026-03-24T00:08:13.967287+00:00",
        "posted": "5/30/2025 11:40:09 PM by DPS\\bbschwarz",
        "entities": {
          "suspects": [],
          "charges": [],
          "bac": null,
          "facility": {
            "code": "FCC",
            "name": "Fairbanks Correctional Center"
          },
          "bail": {
            "status": "unknown",
            "amount": null
          },
          "outcome": "arrested",
          "incident_datetime": null,
          "co_agencies": [],
          "address_detail": "approximately 1755 hours Tok AST received a report of a trespassing",
          "detachment": "D Detachment",
          "officer_id": "bbschwarz"
        },
        "lat": 63.3367,
        "lng": -142.9856,
        "relatedSignalIds": [],
        "impactScore": 70
      },
      {
        "hash": "188cb0f874eb7892d66961f02cb5e534",
        "id": "AK25052087",
        "source": "Alaska State Troopers",
        "category": "Safety",
        "title": "AST Assault DV: Tok [AK25052087]",
        "link": "https://dailydispatch.dps.alaska.gov/Home/DisplayIncident?incidentNumber=AK25052087",
        "sourceUrl": "https://dailydispatch.dps.alaska.gov",
        "articleUrl": "https://dailydispatch.dps.alaska.gov/Home/DisplayIncident?incidentNumber=AK25052087",
        "favicon": "https://www.dps.alaska.gov/favicon.ico",
        "location": "Tok",
        "incident_type": "Assault DV",
        "summary": "On 5/30/2025, Alaska State Troopers in Tok responded to an Assault DV. Investigation revealed Wilbur Karmun to have committed Assault in the Fourth Degree and Assault in the Presence of a Child. Wilbur was arrested and charged.",
        "dataTag": "[Region: Interior] [Category: Law Enforcement]",
        "sourceAttribution": "Source: Alaska State Troopers Daily Dispatch",
        "section": "Safety",
        "sourceLean": "neutral",
        "topic": "Assault DV",
        "timestamp": "2025-05-30T23:38:20+00:00",
        "scraped_at": "2026-03-24T00:08:13.967017+00:00",
        "posted": "5/30/2025 11:38:20 PM by DPS\\cdbuie",
        "entities": {
          "suspects": [],
          "charges": [],
          "bac": null,
          "facility": null,
          "bail": {
            "status": "unknown",
            "amount": null
          },
          "outcome": "arrested",
          "incident_datetime": null,
          "co_agencies": [],
          "address_detail": "revealed Wilbur Karmun to have committed Assault in the Fourth Degree",
          "detachment": "D Detachment",
          "officer_id": "cdbuie"
        },
        "lat": 63.3367,
        "lng": -142.9856,
        "relatedSignalIds": []
      },
      {
        "hash": "15f169fa999222443318a05cbc7f1f2b",
        "id": "AK25052058",
        "source": "Alaska State Troopers",
        "category": "Safety",
        "title": "AST Trespassing/VCOR: Tok [AK25052058]",
        "link": "https://dailydispatch.dps.alaska.gov/Home/DisplayIncident?incidentNumber=AK25052058",
        "sourceUrl": "https://dailydispatch.dps.alaska.gov",
        "articleUrl": "https://dailydispatch.dps.alaska.gov/Home/DisplayIncident?incidentNumber=AK25052058",
        "favicon": "https://www.dps.alaska.gov/favicon.ico",
        "location": "Tok",
        "incident_type": "Trespassing/VCOR",
        "summary": "On May 30th, 2025, at approximately 1755 hours Tok AST received a report of a trespassing. Investigation found Roylon Mark, age 39 of Tetlin, had committed the crimes of Trespassing II and VCOR x8. He was arrested and remanded to FCC.",
        "dataTag": "[Region: Interior] [Category: Law Enforcement]",
        "sourceAttribution": "Multiple Sources (2 reports)",
        "section": "Safety",
        "sourceLean": "neutral",
        "topic": "Trespassing/VCOR",
        "timestamp": "2025-05-30T23:40:09+00:00",
        "scraped_at": "2026-03-24T00:08:13.967287+00:00",
        "posted": "5/30/2025 11:40:09 PM by DPS\\bbschwarz",
        "entities": {
          "suspects": [],
          "charges": [],
          "bac": null,
          "facility": {
            "code": "FCC",
            "name": "Fairbanks Correctional Center"
          },
          "bail": {
            "status": "unknown",
            "amount": null
          },
          "outcome": "arrested",
          "incident_datetime": null,
          "co_agencies": [],
          "address_detail": "approximately 1755 hours Tok AST received a report of a trespassing",
          "detachment": "D Detachment",
          "officer_id": "bbschwarz"
        },
        "lat": 63.3367,
        "lng": -142.9856,
        "relatedSignalIds": [
          "80bf6c54ac89d4979c8e43cb665390e8",
          "2fe4a75ac8fe2054f7e8bd3ec5f5ceb4",
          "21005a1aec05868317f6315e030a70df",
          "37db83d95532bb01ab952ddd98f1c990",
          "a9eb1326443207df38d1ebcd214452bb"
        ],
        "impactScore": 100
      },
      {
        "hash": "188cb0f874eb7892d66961f02cb5e534",
        "id": "AK25052087",
        "source": "Alaska State Troopers",
        "category": "Safety",
        "title": "AST Assault DV: Tok [AK25052087]",
        "link": "https://dailydispatch.dps.alaska.gov/Home/DisplayIncident?incidentNumber=AK25052087",
        "sourceUrl": "https://dailydispatch.dps.alaska.gov",
        "articleUrl": "https://dailydispatch.dps.alaska.gov/Home/DisplayIncident?incidentNumber=AK25052087",
        "favicon": "https://www.dps.alaska.gov/favicon.ico",
        "location": "Tok",
        "incident_type": "Assault DV",
        "summary": "On 5/30/2025, Alaska State Troopers in Tok responded to an Assault DV. Investigation revealed Wilbur Karmun to have committed Assault in the Fourth Degree and Assault in the Presence of a Child. Wilbur was arrested and charged.",
        "dataTag": "[Region: Interior] [Category: Law Enforcement]",
        "sourceAttribution": "Source: Alaska State Troopers Daily Dispatch",
        "section": "Safety",
        "sourceLean": "neutral",
        "topic": "Assault DV",
        "timestamp": "2025-05-30T23:38:20+00:00",
        "scraped_at": "2026-03-24T00:08:13.967017+00:00",
        "posted": "5/30/2025 11:38:20 PM by DPS\\cdbuie",
        "entities": {
          "suspects": [],
          "charges": [],
          "bac": null,
          "facility": null,
          "bail": {
            "status": "unknown",
            "amount": null
          },
          "outcome": "arrested",
          "incident_datetime": null,
          "co_agencies": [],
          "address_detail": "revealed Wilbur Karmun to have committed Assault in the Fourth Degree",
          "detachment": "D Detachment",
          "officer_id": "cdbuie"
        },
        "lat": 63.3367,
        "lng": -142.9856,
        "impactScore": 100,
        "relatedSignalIds": [
          "ef7cb3073fa15576b23313ac25e0ce96",
          "0b0dc44fccc06a5ef34971c544e24c8b",
          "c3c57282768d65249ea8d23a73425df5",
          "b695371469bea203ffed27956f183fab",
          "4caac34fc7898637094386658fb47bba"
        ]
      },
      {
        "hash": "15f169fa999222443318a05cbc7f1f2b",
        "id": "AK25052058",
        "source": "Alaska State Troopers",
        "category": "Safety",
        "title": "AST Trespassing/VCOR: Tok [AK25052058]",
        "link": "https://dailydispatch.dps.alaska.gov/Home/DisplayIncident?incidentNumber=AK25052058",
        "sourceUrl": "https://dailydispatch.dps.alaska.gov",
        "articleUrl": "https://dailydispatch.dps.alaska.gov/Home/DisplayIncident?incidentNumber=AK25052058",
        "favicon": "https://www.dps.alaska.gov/favicon.ico",
        "location": "Tok",
        "incident_type": "Trespassing/VCOR",
        "summary": "On May 30th, 2025, at approximately 1755 hours Tok AST received a report of a trespassing. Investigation found Roylon Mark, age 39 of Tetlin, had committed the crimes of Trespassing II and VCOR x8. He was arrested and remanded to FCC.",
        "dataTag": "[Region: Interior] [Category: Law Enforcement]",
        "sourceAttribution": "Multiple Sources (2 reports)",
        "section": "Safety",
        "sourceLean": "neutral",
        "topic": "Trespassing/VCOR",
        "timestamp": "2025-05-30T23:40:09+00:00",
        "scraped_at": "2026-03-24T00:08:13.967287+00:00",
        "posted": "5/30/2025 11:40:09 PM by DPS\\bbschwarz",
        "entities": {
          "suspects": [],
          "charges": [],
          "bac": null,
          "facility": {
            "code": "FCC",
            "name": "Fairbanks Correctional Center"
          },
          "bail": {
            "status": "unknown",
            "amount": null
          },
          "outcome": "arrested",
          "incident_datetime": null,
          "co_agencies": [],
          "address_detail": "approximately 1755 hours Tok AST received a report of a trespassing",
          "detachment": "D Detachment",
          "officer_id": "bbschwarz"
        },
        "lat": 63.3367,
        "lng": -142.9856,
        "relatedSignalIds": [
          "80bf6c54ac89d4979c8e43cb665390e8",
          "2fe4a75ac8fe2054f7e8bd3ec5f5ceb4",
          "21005a1aec05868317f6315e030a70df",
          "37db83d95532bb01ab952ddd98f1c990",
          "a9eb1326443207df38d1ebcd214452bb"
        ],
        "impactScore": 100
      },
      {
        "hash": "188cb0f874eb7892d66961f02cb5e534",
        "id": "AK25052087",
        "source": "Alaska State Troopers",
        "category": "Safety",
        "title": "AST Assault DV: Tok [AK25052087]",
        "link": "https://dailydispatch.dps.alaska.gov/Home/DisplayIncident?incidentNumber=AK25052087",
        "sourceUrl": "https://dailydispatch.dps.alaska.gov",
        "articleUrl": "https://dailydispatch.dps.alaska.gov/Home/DisplayIncident?incidentNumber=AK25052087",
        "favicon": "https://www.dps.alaska.gov/favicon.ico",
        "location": "Tok",
        "incident_type": "Assault DV",
        "summary": "On 5/30/2025, Alaska State Troopers in Tok responded to an Assault DV. Investigation revealed Wilbur Karmun to have committed Assault in the Fourth Degree and Assault in the Presence of a Child. Wilbur was arrested and charged.",
        "dataTag": "[Region: Interior] [Category: Law Enforcement]",
        "sourceAttribution": "Source: Alaska State Troopers Daily Dispatch",
        "section": "Safety",
        "sourceLean": "neutral",
        "topic": "Assault DV",
        "timestamp": "2025-05-30T23:38:20+00:00",
        "scraped_at": "2026-03-24T00:08:13.967017+00:00",
        "posted": "5/30/2025 11:38:20 PM by DPS\\cdbuie",
        "entities": {
          "suspects": [],
          "charges": [],
          "bac": null,
          "facility": null,
          "bail": {
            "status": "unknown",
            "amount": null
          },
          "outcome": "arrested",
          "incident_datetime": null,
          "co_agencies": [],
          "address_detail": "revealed Wilbur Karmun to have committed Assault in the Fourth Degree",
          "detachment": "D Detachment",
          "officer_id": "cdbuie"
        },
        "lat": 63.3367,
        "lng": -142.9856,
        "impactScore": 100,
        "relatedSignalIds": [
          "ef7cb3073fa15576b23313ac25e0ce96",
          "0b0dc44fccc06a5ef34971c544e24c8b",
          "c3c57282768d65249ea8d23a73425df5",
          "b695371469bea203ffed27956f183fab",
          "4caac34fc7898637094386658fb47bba"
        ]
      },
      {
        "hash": "15f169fa999222443318a05cbc7f1f2b",
        "id": "AK25052058",
        "source": "Alaska State Troopers",
        "category": "Safety",
        "title": "AST Trespassing/VCOR: Tok [AK25052058]",
        "link": "https://dailydispatch.dps.alaska.gov/Home/DisplayIncident?incidentNumber=AK25052058",
        "sourceUrl": "https://dailydispatch.dps.alaska.gov",
        "articleUrl": "https://dailydispatch.dps.alaska.gov/Home/DisplayIncident?incidentNumber=AK25052058",
        "favicon": "https://www.dps.alaska.gov/favicon.ico",
        "location": "Tok",
        "incident_type": "Trespassing/VCOR",
        "summary": "On May 30th, 2025, at approximately 1755 hours Tok AST received a report of a trespassing. Investigation found Roylon Mark, age 39 of Tetlin, had committed the crimes of Trespassing II and VCOR x8. He was arrested and remanded to FCC.",
        "dataTag": "[Region: Interior] [Category: Law Enforcement]",
        "sourceAttribution": "Multiple Sources (2 reports)",
        "section": "Safety",
        "sourceLean": "neutral",
        "topic": "Trespassing/VCOR",
        "timestamp": "2025-05-30T23:40:09+00:00",
        "scraped_at": "2026-03-24T00:08:13.967287+00:00",
        "posted": "5/30/2025 11:40:09 PM by DPS\\bbschwarz",
        "entities": {
          "suspects": [],
          "charges": [],
          "bac": null,
          "facility": {
            "code": "FCC",
            "name": "Fairbanks Correctional Center"
          },
          "bail": {
            "status": "unknown",
            "amount": null
          },
          "outcome": "arrested",
          "incident_datetime": null,
          "co_agencies": [],
          "address_detail": "approximately 1755 hours Tok AST received a report of a trespassing",
          "detachment": "D Detachment",
          "officer_id": "bbschwarz"
        },
        "lat": 63.3367,
        "lng": -142.9856,
        "relatedSignalIds": [
          "80bf6c54ac89d4979c8e43cb665390e8",
          "2fe4a75ac8fe2054f7e8bd3ec5f5ceb4",
          "21005a1aec05868317f6315e030a70df",
          "37db83d95532bb01ab952ddd98f1c990",
          "a9eb1326443207df38d1ebcd214452bb"
        ],
        "impactScore": 100
      },
      {
        "hash": "188cb0f874eb7892d66961f02cb5e534",
        "id": "AK25052087",
        "source": "Alaska State Troopers",
        "category": "Safety",
        "title": "AST Assault DV: Tok [AK25052087]",
        "link": "https://dailydispatch.dps.alaska.gov/Home/DisplayIncident?incidentNumber=AK25052087",
        "sourceUrl": "https://dailydispatch.dps.alaska.gov",
        "articleUrl": "https://dailydispatch.dps.alaska.gov/Home/DisplayIncident?incidentNumber=AK25052087",
        "favicon": "https://www.dps.alaska.gov/favicon.ico",
        "location": "Tok",
        "incident_type": "Assault DV",
        "summary": "On 5/30/2025, Alaska State Troopers in Tok responded to an Assault DV. Investigation revealed Wilbur Karmun to have committed Assault in the Fourth Degree and Assault in the Presence of a Child. Wilbur was arrested and charged.",
        "dataTag": "[Region: Interior] [Category: Law Enforcement]",
        "sourceAttribution": "Source: Alaska State Troopers Daily Dispatch",
        "section": "Safety",
        "sourceLean": "neutral",
        "topic": "Assault DV",
        "timestamp": "2025-05-30T23:38:20+00:00",
        "scraped_at": "2026-03-24T00:08:13.967017+00:00",
        "posted": "5/30/2025 11:38:20 PM by DPS\\cdbuie",
        "entities": {
          "suspects": [],
          "charges": [],
          "bac": null,
          "facility": null,
          "bail": {
            "status": "unknown",
            "amount": null
          },
          "outcome": "arrested",
          "incident_datetime": null,
          "co_agencies": [],
          "address_detail": "revealed Wilbur Karmun to have committed Assault in the Fourth Degree",
          "detachment": "D Detachment",
          "officer_id": "cdbuie"
        },
        "lat": 63.3367,
        "lng": -142.9856,
        "impactScore": 100,
        "relatedSignalIds": [
          "ef7cb3073fa15576b23313ac25e0ce96",
          "0b0dc44fccc06a5ef34971c544e24c8b",
          "c3c57282768d65249ea8d23a73425df5",
          "b695371469bea203ffed27956f183fab",
          "4caac34fc7898637094386658fb47bba"
        ]
      }
    ],
    "impactScore": 100
  },
  {
    "hash": "188cb0f874eb7892d66961f02cb5e534",
    "id": "AK25052087",
    "source": "Alaska State Troopers",
    "category": "Safety",
    "title": "AST Assault DV: Tok [AK25052087]",
    "link": "https://dailydispatch.dps.alaska.gov/Home/Search?incidentNumber=AK25052087",
    "sourceUrl": "https://dailydispatch.dps.alaska.gov",
    "articleUrl": "https://dailydispatch.dps.alaska.gov/Home/Search?incidentNumber=AK25052087",
    "favicon": "https://www.dps.alaska.gov/favicon.ico",
    "location": "Tok",
    "incident_type": "Assault DV",
    "summary": "On 5/30/2025, Alaska State Troopers in Tok responded to an Assault DV. Investigation revealed Wilbur Karmun to have committed Assault in the Fourth Degree and Assault in the Presence of a Child. Wilbur was arrested and charged.",
    "dataTag": "[Region: Interior] [Category: Law Enforcement]",
    "sourceAttribution": "Source: Alaska State Troopers Daily Dispatch",
    "section": "Safety",
    "sourceLean": "neutral",
    "topic": "Assault DV",
    "timestamp": "2025-05-30T23:38:20+00:00",
    "scraped_at": "2026-03-24T00:08:13.967017+00:00",
    "posted": "5/30/2025 11:38:20 PM by DPS\\cdbuie",
    "entities": {
      "suspects": [],
      "charges": [],
      "bac": null,
      "facility": null,
      "bail": {
        "status": "unknown",
        "amount": null
      },
      "outcome": "arrested",
      "incident_datetime": null,
      "co_agencies": [],
      "address_detail": "revealed Wilbur Karmun to have committed Assault in the Fourth Degree",
      "detachment": "D Detachment",
      "officer_id": "cdbuie"
    },
    "lat": 63.3367,
    "lng": -142.9856
  },
  {
    "hash": "e96f4e368da42b1346617811f93ebe2d",
    "id": "AK25124330",
    "source": "Alaska State Troopers",
    "category": "Safety",
    "title": "AST Warrant Arrest: North Pole [AK25124330]",
    "link": "https://dailydispatch.dps.alaska.gov/Home/DisplayIncident?incidentNumber=AK25124330",
    "sourceUrl": "https://dailydispatch.dps.alaska.gov",
    "articleUrl": "https://dailydispatch.dps.alaska.gov/Home/DisplayIncident?incidentNumber=AK25124330",
    "favicon": "https://www.dps.alaska.gov/favicon.ico",
    "location": "North Pole",
    "incident_type": "Warrant Arrest",
    "summary": "On 05/30/2025 at approximately 2235 hours, a Trooper recognized Patrick Knott at the liquor well. The Trooper was aware Knott had multiple warrants and arrested him without incident. He had a $30,000 with 10% posting warrant, a $1000 with 10% posting warrant, and a $100 unsecured warrant. He was tra...",
    "dataTag": "[Region: Interior] [Category: Law Enforcement]",
    "sourceAttribution": "Source: Alaska State Troopers Daily Dispatch",
    "section": "Safety",
    "sourceLean": "neutral",
    "topic": "Warrant Arrest",
    "timestamp": "2025-05-30T23:28:25+00:00",
    "scraped_at": "2026-03-24T00:08:13.966681+00:00",
    "posted": "5/30/2025 11:28:25 PM by DPS\\hrchurness",
    "entities": {
      "suspects": [],
      "charges": [],
      "bac": null,
      "facility": {
        "code": "FCC",
        "name": "Fairbanks Correctional Center"
      },
      "bail": {
        "status": "unknown",
        "amount": null
      },
      "outcome": "arrested",
      "incident_datetime": "2025-05-30T22:35:00+00:00",
      "co_agencies": [],
      "address_detail": null,
      "detachment": "D Detachment",
      "officer_id": "hrchurness",
      "reporting_latency_hours": 0.9
    },
    "lat": 64.7511,
    "lng": -147.3494,
    "relatedSignalIds": [
      "00dd896be833e0d9a5b5347897dfd05c",
      "9838ac082ed176cd56558ba090de844f",
      "add5bae52bbb148156877d7fa929f813",
      "b8f5b7eb180e578ff3d16c2c2817af02",
      "7b1fc4493cc0260a976715a310773599"
    ],
    "impactScore": 100
  },
  {
    "hash": "fef69b32d07d91e0dc827637524a4006",
    "title": "New Study Links Saxitoxin to Deaths of Northern Fur Seals in the Southeast Bering Sea",
    "summary": "New research published in the journal Marine Mammal Science establishes for the first time a link between the neurotoxin saxitoxin, accumulated during harmful algal blooms, and deaths of laaqudan (in Unangam Tunuu, the first language of Unangax\u0302 or the Aleut Peoples), or northern fur seals ( Callorhinus ursisnus ), in the southeast Bering Sea. In the study, researchers collected and analyzed data related to the discovery of 10 dead northern fur seals and hundreds of dead, mostly benthic, fish that washed...",
    "source": "Alaska Ocean Observing",
    "sourceUrl": "Alaska Ocean Observing",
    "articleUrl": "https://aoos.org/new-study-links-saxitoxin-to-deaths-of-northern-fur-seals-in-the-southeast-bering-sea/",
    "url": "https://aoos.org/new-study-links-saxitoxin-to-deaths-of-northern-fur-seals-in-the-southeast-bering-sea/",
    "timestamp": "2025-05-30T18:49:50+00:00",
    "topic": "Science",
    "section": "Science"
  },
  {
    "hash": "03cb7070bd6ce49b97ebb08c42ec7ce8",
    "id": "AK25051899",
    "source": "Alaska State Troopers",
    "category": "Safety",
    "title": "AST Assault DV: Delta Junction [AK25051899]",
    "link": "https://dailydispatch.dps.alaska.gov/Home/DisplayIncident?incidentNumber=AK25051899",
    "sourceUrl": "https://dailydispatch.dps.alaska.gov",
    "articleUrl": "https://dailydispatch.dps.alaska.gov/Home/DisplayIncident?incidentNumber=AK25051899",
    "favicon": "https://www.dps.alaska.gov/favicon.ico",
    "location": "Delta Junction",
    "incident_type": "Assault DV",
    "summary": "On 5-30-25, Delta Junction AST received a report of an assault near Salcha Ave. Investigation showed one party was scratched during an argument which turned slightly physical. A juvenile was present in the residence. Charges are being forwarded over for review and parties separated.",
    "dataTag": "[Region: Interior] [Category: Law Enforcement]",
    "sourceAttribution": "Source: Alaska State Troopers Daily Dispatch",
    "section": "Safety",
    "sourceLean": "neutral",
    "topic": "Assault DV",
    "timestamp": "2025-05-30T18:07:19+00:00",
    "scraped_at": "2026-03-24T00:08:13.966365+00:00",
    "posted": "5/30/2025 6:07:19 PM by DPS\\cihudson",
    "entities": {
      "suspects": [],
      "charges": [],
      "bac": null,
      "facility": null,
      "bail": {
        "status": "unknown",
        "amount": null
      },
      "outcome": "unknown",
      "incident_datetime": null,
      "co_agencies": [],
      "address_detail": "AST received a report of an assault near Salcha Ave",
      "detachment": "D Detachment",
      "officer_id": "cihudson"
    },
    "lat": 64.0378,
    "lng": -145.7317,
    "relatedSignalIds": [
      "57fc56f9fdba94f9391a88b3ee58bd72",
      "5c8333753d208837d97f639b827fd2b9",
      "a33dad35cdbbe4a954a12a41ec391dc2",
      "c32b277cc1800b13eff39fc14bf2e0d7",
      "5de2832bd9e97700612116db14da72e2"
    ],
    "impactScore": 100
  },
  {
    "hash": "e9d515ab239b2a763ad3608c810f1c95",
    "id": "AK25051994",
    "source": "Alaska State Troopers",
    "category": "Safety",
    "title": "AST DUI / VCOR: Delta Junction [AK25051994]",
    "link": "https://dailydispatch.dps.alaska.gov/Home/DisplayIncident?incidentNumber=AK25051994",
    "sourceUrl": "https://dailydispatch.dps.alaska.gov",
    "articleUrl": "https://dailydispatch.dps.alaska.gov/Home/DisplayIncident?incidentNumber=AK25051994",
    "favicon": "https://www.dps.alaska.gov/favicon.ico",
    "location": "Delta Junction",
    "incident_type": "DUI / VCOR",
    "summary": "On 5-30-25, Delta Junction AST received a report of a male asleep in the driver seat of a vehicle near Kimball St. EMS and Delta AST responded. Investigation led to Jeremy Brown-Pabon being arrested for DUI. Jeremy provided a sample on the Datamaster resulting in a BrAC of .180. He was transported t...",
    "dataTag": "[Region: Interior] [Category: Law Enforcement]",
    "sourceAttribution": "Source: Alaska State Troopers Daily Dispatch",
    "section": "Safety",
    "sourceLean": "neutral",
    "topic": "DUI / VCOR",
    "timestamp": "2025-05-30T16:50:43+00:00",
    "scraped_at": "2026-03-24T00:08:13.965999+00:00",
    "posted": "5/30/2025 4:50:43 PM by DPS\\cihudson",
    "entities": {
      "suspects": [],
      "charges": [
        "DUI"
      ],
      "bac": null,
      "facility": {
        "code": "FCC",
        "name": "Fairbanks Correctional Center"
      },
      "bail": {
        "status": "unknown",
        "amount": null
      },
      "outcome": "arrested",
      "incident_datetime": null,
      "co_agencies": [],
      "address_detail": "AST received a report of a male asleep in the driver seat of a vehicle near Kimball St",
      "detachment": "D Detachment",
      "officer_id": "cihudson"
    },
    "lat": 64.0378,
    "lng": -145.7317,
    "relatedSignalIds": [
      "57fc56f9fdba94f9391a88b3ee58bd72",
      "b1ef19069debbd852a8ae737614e76a7",
      "5c8333753d208837d97f639b827fd2b9",
      "fe74d73f5014e02409f668a9d0f2d557",
      "a33dad35cdbbe4a954a12a41ec391dc2"
    ],
    "impactScore": 100
  },
  {
    "hash": "6ca572014bb65bdf10112a497c72ccea",
    "id": "AK25051730",
    "source": "Alaska State Troopers",
    "category": "Safety",
    "title": "AST Death Investigation: Healy [AK25051730]",
    "link": "https://dailydispatch.dps.alaska.gov/Home/DisplayIncident?incidentNumber=AK25051730",
    "sourceUrl": "https://dailydispatch.dps.alaska.gov",
    "articleUrl": "https://dailydispatch.dps.alaska.gov/Home/DisplayIncident?incidentNumber=AK25051730",
    "favicon": "https://www.dps.alaska.gov/favicon.ico",
    "location": "Healy",
    "incident_type": "Death Investigation",
    "summary": "On 05/30/2025 at 0619 hours the Alaska State Troopers received a report of CPR in progress near Mile 260 Parks Highway. Tri-Valley EMS responded and provided care. Ultimately, recusation efforts were not effective and patient was pronounced deceased. The next of kin were notified and the body was re...",
    "dataTag": "[Region: Statewide] [Category: Law Enforcement]",
    "sourceAttribution": "Source: Alaska State Troopers Daily Dispatch",
    "section": "Safety",
    "sourceLean": "neutral",
    "topic": "Death Investigation",
    "timestamp": "2025-05-30T16:41:17+00:00",
    "scraped_at": "2026-03-24T00:08:13.965713+00:00",
    "posted": "5/30/2025 4:41:17 PM by DPS\\dwbozman",
    "entities": {
      "suspects": [],
      "charges": [],
      "bac": null,
      "facility": null,
      "bail": {
        "status": "unknown",
        "amount": null
      },
      "outcome": "fatal",
      "incident_datetime": "2025-05-30T06:19:00+00:00",
      "co_agencies": [],
      "address_detail": "Mile 260 Parks Highway",
      "detachment": "D Detachment",
      "officer_id": "dwbozman",
      "reporting_latency_hours": 10.4
    },
    "lat": 64.0134359771237,
    "lng": -149.141473557352,
    "relatedSignalIds": [
      "a8295cd7f213c40a3ce7c0fe20e59044",
      "30372f144f5337d0576235c24f15000c",
      "b77504dc11ff005d9709eb4d30f450d6"
    ],
    "impactScore": 100
  },
  {
    "hash": "fc872cb9bd1591c6386ce701d5c19119",
    "title": "A new era of political disenfranchisement: soft disenrollment?",
    "summary": "Phoenix Johnson T\u0142ingit & Haida In the heart of Southeast Alaska, a quiet storm brews within the Alaskan Native tribal nation of the Central Council of the Tlingit and Haida Indian Tribes, exposing fractures in governance, identity, and power that mirror some of the most dangerous political undercurrents shaping national policy today under Trump. This is not just a story of internal conflict, it\u2019s a warning for Indian Country. The tribe\u2019s executive council quietly rammed through a controversial constitutional rewrite while appearing to sideline valid parliamentary motions that gutted delegations. In the 90th annual tribal assembly that took place April 16-18, an already reduced Seattle delegation of 25 was the sacrificial symbol in a larger campaign...",
    "source": "Indian Country Today Alaska",
    "sourceUrl": "Indian Country Today Alaska",
    "articleUrl": "https://ictnews.org/opinion/a-new-era-of-political-disenfranchisement-soft-disenrollment/",
    "url": "https://ictnews.org/opinion/a-new-era-of-political-disenfranchisement-soft-disenrollment/",
    "timestamp": "2025-05-30T16:37:31+00:00",
    "topic": "Native",
    "section": "Native"
  },
  {
    "hash": "6444948fe0729a565e31150e7bb76f71",
    "title": "NOTICE OF REQUEST FOR PROPOSALS FOR LAND DISPOSAL \u2013 Lot 2, Block 7A, Tidewater Development Park",
    "summary": "The City is requesting proposals for the following City property (Click RFP number for more details): LD-RFP-25-03 Addendum to LD-RFP-25-03 Property: Lot 2, Block 7A, Tidewater Development Park Please Contact Amanda Hadley Coward, City Planner, for additional details at planning@cityofcordova.net or...",
    "source": "Cordova City",
    "sourceUrl": "Cordova City",
    "articleUrl": "https://www.cityofcordova.net/notice-of-request-for-proposals-for-land-disposal-lot-2-block-7a-tidewater-development-park/?utm_source=rss&utm_medium=rss&utm_campaign=notice-of-request-for-proposals-for-land-disposal-lot-2-block-7a-tidewater-development-park",
    "url": "https://www.cityofcordova.net/notice-of-request-for-proposals-for-land-disposal-lot-2-block-7a-tidewater-development-park/?utm_source=rss&utm_medium=rss&utm_campaign=notice-of-request-for-proposals-for-land-disposal-lot-2-block-7a-tidewater-development-park",
    "timestamp": "2025-05-30T16:00:22+00:00",
    "topic": "Government",
    "section": "Government"
  },
  {
    "hash": "981026c4b9e03a484a6122f1627af9f5",
    "title": "TUESDAY: Post-Session Constituent Debrief",
    "summary": "Join Representative Fields and Senator Tobin for a post-session constituent debrief on Tuesday, June 3rd from 5:30 pm to 6:30 pm The post TUESDAY: Post-Session Constituent Debrief appeared first on Alaska Senate Majority .",
    "source": "Alaska Senate Majority",
    "sourceUrl": "Alaska Senate Majority",
    "articleUrl": "https://open.substack.com/pub/lgtobin/p/tuesday-post-session-constituent?r=22fcg4&utm_campaign=post&utm_medium=web#new_tab&utm_source=rss&utm_medium=rss&utm_campaign=tuesday-post-session-constituent-debrief",
    "url": "https://open.substack.com/pub/lgtobin/p/tuesday-post-session-constituent?r=22fcg4&utm_campaign=post&utm_medium=web#new_tab&utm_source=rss&utm_medium=rss&utm_campaign=tuesday-post-session-constituent-debrief",
    "timestamp": "2025-05-30T15:34:01+00:00",
    "topic": "Government",
    "section": "Government"
  },
  {
    "hash": "3d18b4f378c20c051596700dd5907560",
    "id": "AK25051891",
    "source": "Alaska State Troopers",
    "category": "Safety",
    "title": "AST Theft: North Pole [AK25051891]",
    "link": "https://dailydispatch.dps.alaska.gov/Home/DisplayIncident?incidentNumber=AK25051891",
    "sourceUrl": "https://dailydispatch.dps.alaska.gov",
    "articleUrl": "https://dailydispatch.dps.alaska.gov/Home/DisplayIncident?incidentNumber=AK25051891",
    "favicon": "https://www.dps.alaska.gov/favicon.ico",
    "location": "North Pole",
    "incident_type": "Theft",
    "summary": "On 5/30/25 at approximately 1220 hours, the homeowner at a residence off Lineman Drive in North Pole reported that their red Oldtown tandem kayak was stolen sometime over the winter. The kayak was estimated to be worth $1,500.00 and had distinctive damage to the body. Anyone with information about t...",
    "dataTag": "[Region: Interior] [Category: Law Enforcement]",
    "sourceAttribution": "Source: Alaska State Troopers Daily Dispatch",
    "section": "Safety",
    "sourceLean": "neutral",
    "topic": "Theft",
    "timestamp": "2025-05-30T15:30:51+00:00",
    "scraped_at": "2026-03-24T00:08:13.965233+00:00",
    "posted": "5/30/2025 3:30:51 PM by DPS\\hlculley",
    "entities": {
      "suspects": [],
      "charges": [],
      "bac": null,
      "facility": null,
      "bail": {
        "status": "unknown",
        "amount": null
      },
      "outcome": "unknown",
      "incident_datetime": null,
      "co_agencies": [],
      "address_detail": "a residence off Lineman Drive in North Pole reported that their red Oldtown tandem kayak was stolen sometime over the winter",
      "detachment": "D Detachment",
      "officer_id": "hlculley"
    },
    "lat": 64.7511,
    "lng": -147.3494,
    "relatedSignalIds": [
      "1a100fed7f18c85f54a763fb7936c215",
      "f1836163a51772b30264f7a56ef2a9b9",
      "cd4a790adb08ceafea9934f053d1acc4",
      "e643e985d23800fbb3fc3fbe878d0091",
      "48881f4cd52ccaa0a7e87dd688cb6dc5"
    ],
    "impactScore": 100
  },
  {
    "hash": "32726516c92a8a384f7efc29a8eacb87",
    "id": "AK25051800",
    "source": "Alaska State Troopers",
    "category": "Safety",
    "title": "AST Mail Theft: Fairbanks [AK25051800]",
    "link": "https://dailydispatch.dps.alaska.gov/Home/DisplayIncident?incidentNumber=AK25051800",
    "sourceUrl": "https://dailydispatch.dps.alaska.gov",
    "articleUrl": "https://dailydispatch.dps.alaska.gov/Home/DisplayIncident?incidentNumber=AK25051800",
    "favicon": "https://www.dps.alaska.gov/favicon.ico",
    "location": "Fairbanks",
    "incident_type": "Mail Theft",
    "summary": "On 5/30/25 at approximately 1030 hours, the homeowner at a residence off Chinook Drive in Fairbanks reported that an amazon box with products worth approximately $100 was stolen. The suspect walked up to the house, stole the box and left in a small blue car. Anyone with information about this crime....",
    "dataTag": "[Region: Interior] [Category: Law Enforcement]",
    "sourceAttribution": "Source: Alaska State Troopers Daily Dispatch",
    "section": "Safety",
    "sourceLean": "neutral",
    "topic": "Mail Theft",
    "timestamp": "2025-05-30T15:26:09+00:00",
    "scraped_at": "2026-03-24T00:08:13.964630+00:00",
    "posted": "5/30/2025 3:26:09 PM by DPS\\hlculley",
    "entities": {
      "suspects": [],
      "charges": [],
      "bac": null,
      "facility": null,
      "bail": {
        "status": "unknown",
        "amount": null
      },
      "outcome": "unknown",
      "incident_datetime": null,
      "co_agencies": [],
      "address_detail": "a residence off Chinook Drive in Fairbanks reported that an amazon bo",
      "detachment": "D Detachment",
      "officer_id": "hlculley"
    },
    "lat": 64.8378,
    "lng": -147.7164,
    "relatedSignalIds": [
      "8c179ac85d61590a23d6088e36dc94d1",
      "93b01c8afd57e2663356116eddf8e23d"
    ],
    "impactScore": 90
  },
  {
    "hash": "5bf371bd3a29f099249c66dbb474d1b4",
    "id": "AK25051550",
    "source": "Alaska State Troopers",
    "category": "Safety",
    "title": "AST Fail to Stop, Assault 3 and Reckless Driving: Seward [AK25051550]",
    "link": "https://dailydispatch.dps.alaska.gov/Home/DisplayIncident?incidentNumber=AK25051550",
    "sourceUrl": "https://dailydispatch.dps.alaska.gov",
    "articleUrl": "https://dailydispatch.dps.alaska.gov/Home/DisplayIncident?incidentNumber=AK25051550",
    "favicon": "https://www.dps.alaska.gov/favicon.ico",
    "location": "Seward",
    "incident_type": "Fail to Stop, Assault 3 and Reckless Driving",
    "summary": "On 05/29/2025, at approximately 1543 hrs., AST Dispatch received a report from Seward Police Department (SPD) that a black Dodge Challenger was driving recklessly out of Seward passing multiple people in the center lane and passing people on double yellow traffic lines at a high-rate speed. SPD atte...",
    "dataTag": "[Region: Southcentral] [Category: Law Enforcement]",
    "sourceAttribution": "Source: Alaska State Troopers Daily Dispatch",
    "section": "Safety",
    "sourceLean": "neutral",
    "topic": "Fail to Stop, Assault 3 and Reckless Driving",
    "timestamp": "2025-05-30T10:51:20+00:00",
    "scraped_at": "2026-03-24T00:08:13.962628+00:00",
    "posted": "5/30/2025 10:51:20 AM by DPS\\rlmau",
    "entities": {
      "suspects": [],
      "charges": [
        "Fail to Stop at the Direction of a Peace Officer",
        "Assault 3",
        "Reckless Driving x 2"
      ],
      "bac": null,
      "facility": {
        "code": "Wildwood",
        "name": "Wildwood Correctional Complex"
      },
      "bail": {
        "status": "unknown",
        "amount": null
      },
      "outcome": "arrested",
      "incident_datetime": null,
      "co_agencies": [],
      "address_detail": "a black Dodge Challenger was driving recklessly out of Seward passing multiple people in the center lane and passing people on double yellow tra",
      "detachment": "A Detachment",
      "officer_id": "rlmau"
    },
    "lat": 60.5275844767751,
    "lng": -149.518738974673,
    "relatedSignalIds": [
      "63394d3f0d7d57f32502b8e1ddd907e8",
      "f7641975d74fd3613e711966e0c4cd1a",
      "b494d7dae19891862b94b166147b757d",
      "daae85df990f5f75ef4faf2e9cb18efe",
      "0a6fb67d3a5baa0d8ccc8738382d2347"
    ],
    "impactScore": 100
  },
  {
    "hash": "6bd78d3058c494e6f99bf41e0573197f",
    "id": "AK25051359",
    "source": "Alaska State Troopers",
    "category": "Safety",
    "title": "AST Death Investigation: Glacier View [AK25051359]",
    "link": "https://dailydispatch.dps.alaska.gov/Home/DisplayIncident?incidentNumber=AK25051359",
    "sourceUrl": "https://dailydispatch.dps.alaska.gov",
    "articleUrl": "https://dailydispatch.dps.alaska.gov/Home/DisplayIncident?incidentNumber=AK25051359",
    "favicon": "https://www.dps.alaska.gov/favicon.ico",
    "location": "Glacier View",
    "incident_type": "Death Investigation",
    "summary": "On 05/29/2025, Mat Com dispatch received a 911 call reporting CPR was being conducted on Arlis Riddles (83 years of age) at his home in Glacier View (near mile 100 of the Glenn Hwy). AWT was nearby and responded to assist EMS in life saving measures which were unsuccessful. Investigation revealed th...",
    "dataTag": "[Region: Statewide] [Category: Law Enforcement]",
    "sourceAttribution": "Source: Alaska State Troopers Daily Dispatch",
    "section": "Safety",
    "sourceLean": "neutral",
    "topic": "Death Investigation",
    "timestamp": "2025-05-30T09:14:47+00:00",
    "scraped_at": "2026-03-24T00:08:13.968746+00:00",
    "posted": "5/30/2025 9:14:47 AM by DPS\\dbledford",
    "entities": {
      "suspects": [],
      "charges": [],
      "bac": null,
      "facility": null,
      "bail": {
        "status": "unknown",
        "amount": null
      },
      "outcome": "fatal",
      "incident_datetime": null,
      "co_agencies": [],
      "address_detail": "mile 100 of the Glenn Hwy)",
      "detachment": "AK Wildlife Troopers",
      "officer_id": "dbledford"
    },
    "lat": 61.8042482390066,
    "lng": -147.84333891146,
    "relatedSignalIds": [
      "1a3e3f1ad39315493f39b8359cde843c"
    ],
    "impactScore": 60
  },
  {
    "hash": "3eeef21b5e346353d9d8beffb7aaf1b3",
    "title": "The Arctic This Week Take Five: Week of 26 May, 2025",
    "summary": "Take Five is The Arctic Institute's weekly redux on the Arctic's most important stories, published every Friday. The post The Arctic This Week Take Five: Week of 26 May, 2025 appeared first on The Arctic Institute - Center for Circumpolar Security Studies .",
    "source": "The Arctic Institute",
    "sourceUrl": "The Arctic Institute",
    "articleUrl": "https://www.thearcticinstitute.org/arctic-week-take-five-week-26-may-2025/",
    "url": "https://www.thearcticinstitute.org/arctic-week-take-five-week-26-may-2025/",
    "timestamp": "2025-05-30T07:40:00+00:00",
    "topic": "Research",
    "section": "Research"
  },
  {
    "hash": "1c8d4d907c6fdd8f22f9cd79a75ec5e4",
    "id": "AK25051688",
    "source": "Alaska State Troopers",
    "category": "Safety",
    "title": "AST MICS: Fairbanks [AK25051688]",
    "link": "https://dailydispatch.dps.alaska.gov/Home/DisplayIncident?incidentNumber=AK25051688",
    "sourceUrl": "https://dailydispatch.dps.alaska.gov",
    "articleUrl": "https://dailydispatch.dps.alaska.gov/Home/DisplayIncident?incidentNumber=AK25051688",
    "favicon": "https://www.dps.alaska.gov/favicon.ico",
    "location": "Fairbanks",
    "incident_type": "MICS",
    "summary": "On 05/30/2025 at 0529 hours a Trooper conducted a traffic stop for a registration violation. The driver and only occupant was Macy Nakak. Nakak was cited for driving without a license and no proof insurance. Suspected methamphetamine was seized and will be sent to the crime lab for testing. This cas...",
    "dataTag": "[Region: Interior] [Category: Law Enforcement]",
    "sourceAttribution": "Source: Alaska State Troopers Daily Dispatch",
    "section": "Safety",
    "sourceLean": "neutral",
    "topic": "MICS",
    "timestamp": "2025-05-30T07:05:36+00:00",
    "scraped_at": "2026-03-24T00:08:13.968262+00:00",
    "posted": "5/30/2025 7:05:36 AM by DPS\\hrchurness",
    "entities": {
      "suspects": [],
      "charges": [
        "driving without a license",
        "no proof insurance"
      ],
      "bac": null,
      "facility": null,
      "bail": {
        "status": "cited_released",
        "amount": null
      },
      "outcome": "cited",
      "incident_datetime": "2025-05-30T05:29:00+00:00",
      "co_agencies": [],
      "address_detail": null,
      "detachment": "D Detachment",
      "officer_id": "hrchurness",
      "reporting_latency_hours": 1.6
    },
    "lat": 64.8378,
    "lng": -147.7164,
    "relatedSignalIds": [
      "977f62ffb41e14ac3eb322342c0d5bfc",
      "260eb6ca63b68e9bbf6ef39c3bdef81b",
      "ea197b60a277ec36ac2aa872d2661b5a",
      "2c69603798e5c0e42566f24d6c09751b",
      "75e192ff13d18517e68085a0ae5f0956"
    ],
    "impactScore": 100
  },
  {
    "hash": "62e6013fdd8d900fd8234a9a694c87f6",
    "id": "AK25051620",
    "source": "Alaska State Troopers",
    "category": "Safety",
    "title": "AST DV Criminal Mischief 4: Wasilla [AK25051620]",
    "link": "https://dailydispatch.dps.alaska.gov/Home/DisplayIncident?incidentNumber=AK25051620",
    "sourceUrl": "https://dailydispatch.dps.alaska.gov",
    "articleUrl": "https://dailydispatch.dps.alaska.gov/Home/DisplayIncident?incidentNumber=AK25051620",
    "favicon": "https://www.dps.alaska.gov/favicon.ico",
    "location": "Wasilla",
    "incident_type": "DV Criminal Mischief 4",
    "summary": "On 05/29/2025 at approximately 2012 hours, AST received a report that there was a disturbance at a residence near Spruce Ave in Wasilla. The investigation revealed that Tonimarie Marden, 37 years old of Wasilla, had damaged the property of a domestic partner. Marden was arrested, transported, and re...",
    "dataTag": "[Region: Mat-Su] [Category: Law Enforcement]",
    "sourceAttribution": "Source: Alaska State Troopers Daily Dispatch",
    "section": "Safety",
    "sourceLean": "neutral",
    "topic": "DV Criminal Mischief 4",
    "timestamp": "2025-05-30T02:06:03+00:00",
    "scraped_at": "2026-03-24T00:08:13.963053+00:00",
    "posted": "5/30/2025 2:06:03 AM by DPS\\tjwilson",
    "entities": {
      "suspects": [],
      "charges": [],
      "bac": null,
      "facility": null,
      "bail": {
        "status": "denied",
        "amount": null
      },
      "outcome": "arrested",
      "incident_datetime": "2025-05-29T20:12:00+00:00",
      "co_agencies": [],
      "address_detail": "there was a disturbance at a residence near Spruce Ave in Wasilla",
      "detachment": "B Detachment",
      "officer_id": "tjwilson",
      "reporting_latency_hours": 5.9
    },
    "lat": 61.5809,
    "lng": -149.4401,
    "relatedSignalIds": [
      "3de23535ad9cf0378b33f91466bf5da3",
      "e673bd9a41a5bd545572818608be52eb",
      "0401e470fd9f08a5e66d4b1b8a622694",
      "b58dc21cafdea8a3dae14372c1b45b47",
      "c9e9dabbe91846b2de9483035b2fe102"
    ],
    "impactScore": 100
  },
  {
    "hash": "3d7a2c4b8d7ebbf128921a134b31812a",
    "id": "AK25051660",
    "source": "Alaska State Troopers",
    "category": "Safety",
    "title": "AST Eluding, Warrant Arrest: Fairbanks [AK25051660]",
    "link": "https://dailydispatch.dps.alaska.gov/Home/DisplayIncident?incidentNumber=AK25051660",
    "sourceUrl": "https://dailydispatch.dps.alaska.gov",
    "articleUrl": "https://dailydispatch.dps.alaska.gov/Home/DisplayIncident?incidentNumber=AK25051660",
    "favicon": "https://www.dps.alaska.gov/favicon.ico",
    "location": "Fairbanks",
    "incident_type": "Eluding, Warrant Arrest",
    "summary": "On 05/30/2025 at 0001 hours a Trooper recognized Justin Snyder in a vehicle at the Circle K gas station on Peger Road. The Trooper knew Snyder had a No Bail Parole Violation warrant for Murder 2. Snyder fled in his vehicle and a pursuit ensued. Troopers deployed stop sticks on the vehicle, and Snyde...",
    "dataTag": "[Region: Interior] [Category: Law Enforcement]",
    "sourceAttribution": "Source: Alaska State Troopers Daily Dispatch",
    "section": "Safety",
    "sourceLean": "neutral",
    "topic": "Eluding, Warrant Arrest",
    "timestamp": "2025-05-30T01:52:50+00:00",
    "scraped_at": "2026-03-24T00:08:13.967718+00:00",
    "posted": "5/30/2025 1:52:50 AM by DPS\\hrchurness",
    "entities": {
      "suspects": [],
      "charges": [],
      "bac": null,
      "facility": null,
      "bail": {
        "status": "denied",
        "amount": null
      },
      "outcome": "arrested",
      "incident_datetime": "2025-05-30T00:01:00+00:00",
      "co_agencies": [],
      "address_detail": "the Circle K gas station on Peger Road",
      "detachment": "D Detachment",
      "officer_id": "hrchurness",
      "reporting_latency_hours": 1.9
    },
    "lat": 64.8378,
    "lng": -147.7164,
    "relatedSignalIds": [
      "b921e8142f950c5aac7f2b470b0c76a0",
      "10a1a7565a8532d5f93cafb6ab22af78",
      "260eb6ca63b68e9bbf6ef39c3bdef81b",
      "6bbd7c67bc2d2fa61d8e5b696a35bfbb",
      "1a53a0606eb5eb5eb692a019887763b6"
    ],
    "impactScore": 100
  }
]