[
  {
    "hash": "1fc2420ae21b2cb676ff670ca1aba730",
    "source": "Cook Inlet Region Inc (CIRI)",
    "category": "Native",
    "title": "CIRI Resolves Land Issues",
    "link": "https://www.ciri.com/shareholder-news/ciri-resolves-land-issues/",
    "published": "Thu, 31 Aug 2017 10:00:53 +0000",
    "summary": "Through cooperation and compromise, CIRI settles land issues that result in new revenue streams for the company. Much of the parking lot and trail to access the Matanuska Glacier is on CIRI land. CIRI will now be compensated for the use of its land. Photo by Jason Moore. When it comes to managing CI...",
    "dataTag": "[Region: Mat-Su] [Category: Native]",
    "sourceAttribution": "Source: Cook Inlet Region Inc (CIRI)",
    "imageUrl": "https://www.ciri.com/wp-content/uploads/2017/08/No-tresspassing_crop-300x300.jpg",
    "timestamp": "2017-08-31T10:00:53+00:00",
    "impactScore": 38,
    "region": "Cook Inlet",
    "sector": "native-affairs",
    "urgency": "background",
    "entitySlugs": [
      "ciri"
    ],
    "relatedSignalIds": [
      "ff807885ccc6761e8a99a864c07a36c8",
      "ce46789aac2825df10ebf41ce4c92cfa",
      "9f58583c5c90a4a30b7d9e3c3d2d473b",
      "5be3d02852478bb83ce953e5a617c40c",
      "efa542abe91cf7f91bf66259edaf9fd2"
    ]
  },
  {
    "hash": "90a7e205f0bed2109c3f54262386bec6",
    "source": "Cook Inlet Region Inc (CIRI)",
    "category": "Native",
    "title": "Over 30,000 Indian Trust Settlement Class Members Missing",
    "link": "https://www.ciri.com/shareholder-news/over-30000-indian-trust-settlement-class-members-missing/",
    "published": "Thu, 31 Aug 2017 09:45:03 +0000",
    "summary": "Deadline to Submit Documentation: November 27, 2017 In late 2010, after nearly 15 years of litigation, the class action litigation initiated by key plaintiff Elouise Cobell v. Salazar against the Department of Interior (DOI) settled for $3.4 billion, and then-President Barack Obama signed legislatio...",
    "dataTag": "[Region: Statewide] [Category: Native]",
    "sourceAttribution": "Source: Cook Inlet Region Inc (CIRI)",
    "imageUrl": "https://www.ciri.com/wp-content/uploads/2017/08/Hourglass_crop-300x300.jpg",
    "timestamp": "2017-08-31T09:45:03+00:00",
    "impactScore": 53,
    "region": "Statewide",
    "sector": "native-affairs",
    "urgency": "soon",
    "entitySlugs": [],
    "relatedSignalIds": [
      "2cf0ffe7dd9d230db5030eb140465c50"
    ]
  },
  {
    "hash": "77d73cc0747a5ac597e79e99d756322f",
    "source": "Cook Inlet Region Inc (CIRI)",
    "category": "Native",
    "title": "Shareholder Spotlight",
    "link": "https://www.ciri.com/shareholder-news/shareholder-spotlight/",
    "published": "Thu, 31 Aug 2017 09:40:07 +0000",
    "summary": "Lucy Untiet (left) and Lydia Thorne. Photo by Joel Irwin. Over the years, CIRI has remained focused on its objective of delivering meaningful and sustaining benefits to its shareholders, including direct economic benefits such as quarterly dividends and CIRI Elders\u2019 Settlement Trust payments. So how...",
    "dataTag": "[Region: Southcentral] [Category: Native]",
    "sourceAttribution": "Source: Cook Inlet Region Inc (CIRI)",
    "imageUrl": "https://www.ciri.com/wp-content/uploads/2017/08/lydia-and-lucy_crop-300x300.jpg",
    "timestamp": "2017-08-31T09:40:07+00:00",
    "impactScore": 38,
    "region": "Cook Inlet",
    "sector": "native-affairs",
    "urgency": "background",
    "entitySlugs": [
      "ciri"
    ],
    "relatedSignalIds": [
      "ff807885ccc6761e8a99a864c07a36c8",
      "ce46789aac2825df10ebf41ce4c92cfa",
      "9f58583c5c90a4a30b7d9e3c3d2d473b",
      "5be3d02852478bb83ce953e5a617c40c",
      "efa542abe91cf7f91bf66259edaf9fd2"
    ]
  },
  {
    "hash": "7c244cb6b997a6442551b95520b623cb",
    "source": "Cook Inlet Region Inc (CIRI)",
    "category": "Native",
    "title": "Student Conservation Association 2017 CIRI Youth Crew",
    "link": "https://www.ciri.com/shareholder-news/student-conservation-association-2017-ciri-youth-crew/",
    "published": "Thu, 31 Aug 2017 09:35:32 +0000",
    "summary": "The CIRI Youth Crew at the Fireweed Business Center. Jeff Samuels, SCA partnership director for Alaska, is far right. Photo by Jason Brune. To ensure Alaska Native youth remain connected with their land, culture and heritage, since 2010 CIRI has sponsored a Student Conservation Association (SCA) You...",
    "dataTag": "[Region: Southcentral] [Category: Native]",
    "sourceAttribution": "Source: Cook Inlet Region Inc (CIRI)",
    "imageUrl": "https://www.ciri.com/wp-content/uploads/2017/08/SCA_crop-1-300x300.jpg",
    "timestamp": "2017-08-31T09:35:32+00:00",
    "impactScore": 38,
    "region": "Cook Inlet",
    "sector": "native-affairs",
    "urgency": "background",
    "entitySlugs": [
      "ciri"
    ],
    "relatedSignalIds": [
      "ff807885ccc6761e8a99a864c07a36c8",
      "ce46789aac2825df10ebf41ce4c92cfa",
      "9f58583c5c90a4a30b7d9e3c3d2d473b",
      "5be3d02852478bb83ce953e5a617c40c",
      "efa542abe91cf7f91bf66259edaf9fd2"
    ]
  },
  {
    "hash": "2cf0ffe7dd9d230db5030eb140465c50",
    "source": "Cook Inlet Region Inc (CIRI)",
    "category": "Native",
    "title": "Recipe: Indian Fry Bread",
    "link": "https://www.ciri.com/recipes/recipe-indian-fry-bread/",
    "published": "Thu, 31 Aug 2017 09:30:59 +0000",
    "summary": "Adapted from The Pioneer Woman website, www.thepioneerwoman.com . As the author wrote about this recipe, \u201cIndian Fry Bread [is] a Native American quick bread that\u2019s fried and served either on its own, drizzled with honey, sprinkled with cinnamon sugar, or topped with ground beef and other taco ingre...",
    "dataTag": "[Region: Statewide] [Category: Native]",
    "sourceAttribution": "Source: Cook Inlet Region Inc (CIRI)",
    "imageUrl": "https://www.ciri.com/wp-content/uploads/2017/08/flour-dust-1910046_1920-300x200.jpg",
    "timestamp": "2017-08-31T09:30:59+00:00",
    "impactScore": 38,
    "region": "Statewide",
    "sector": "native-affairs",
    "urgency": "background",
    "entitySlugs": [],
    "relatedSignalIds": [
      "90a7e205f0bed2109c3f54262386bec6"
    ]
  },
  {
    "hash": "fe45289f3f82da6af4abe1c8c2ccc12b",
    "source": "Cook Inlet Region Inc (CIRI)",
    "category": "Native",
    "title": "CIRI Golf Classic Benefits Four Youth Charities",
    "link": "https://www.ciri.com/feature/ciri-golf-classic-benefits-four-youth-charities/",
    "published": "Thu, 31 Aug 2017 09:15:08 +0000",
    "summary": "A group of CIRI volunteers at the 2017 Golf Classic. Photo by Joel Irwin. On a bright and sunny morning, 148 players turned out for CIRI\u2019s 34th Annual Golf Classic, held Friday, Aug. 4 at the Moose Run Golf Course in Anchorage. Thanks to participants and generous corporate sponsors, the Golf Classic...",
    "dataTag": "[Region: Southcentral] [Category: Native]",
    "sourceAttribution": "Source: Cook Inlet Region Inc (CIRI)",
    "imageUrl": "https://www.ciri.com/wp-content/uploads/2017/08/Golf_crop-300x300.jpg",
    "timestamp": "2017-08-31T09:15:08+00:00",
    "impactScore": 38,
    "region": "Cook Inlet",
    "sector": "native-affairs",
    "urgency": "background",
    "entitySlugs": [
      "ciri"
    ],
    "relatedSignalIds": [
      "ff807885ccc6761e8a99a864c07a36c8",
      "ce46789aac2825df10ebf41ce4c92cfa",
      "9f58583c5c90a4a30b7d9e3c3d2d473b",
      "5be3d02852478bb83ce953e5a617c40c",
      "efa542abe91cf7f91bf66259edaf9fd2"
    ]
  }
]