[
  {
    "hash": "48ee3d9f1c1ea0d69ef1300d49637995",
    "title": "April 6, 2015 \u2013 Magnolia Memoir",
    "summary": "Choctaw musician Mela Lee is the front woman of the Los Angeles based band Magnolia Memoir. The band was born out of Mela\u2019s journey to learn more about her late father and her Native heritage. Her five octave vocal range accompanies the cinematic alt-rock style of the group\u2019s creative arrangements....",
    "source": "Indigefi",
    "sourceUrl": "Indigefi",
    "articleUrl": "https://www.indigefi.org/april-6-2015-magnolia-memoir/",
    "url": "https://www.indigefi.org/april-6-2015-magnolia-memoir/",
    "timestamp": "2015-04-06T06:58:34+00:00",
    "topic": "Music & Media",
    "section": "Music & Media"
  }
]